{
  "id": "php/escapecharacters",
  "contentHtml": "<h1>Escape Characters</h1>\n<p>You can escape characters using <span class=\"katex-error\" style=\"color:#cc0000\">\\</span>.</p>\n<pre><code class=\"language-html\"><span class=\"hljs-meta\">&#x3C;!DOCTYPE <span class=\"hljs-keyword\">html</span>></span>\n<span class=\"hljs-tag\">&#x3C;<span class=\"hljs-name\">html</span>></span>\n\n<span class=\"hljs-tag\">&#x3C;<span class=\"hljs-name\">body</span>></span>\n    <span class=\"hljs-meta\">&#x3C;?php\n        $desc = \"Tristan is a \\\"king\\\", type shit.\";\n        echo $desc;\n    ?></span>\n<span class=\"hljs-tag\">&#x3C;/<span class=\"hljs-name\">body</span>></span>\n\n<span class=\"hljs-tag\">&#x3C;/<span class=\"hljs-name\">html</span>></span>\n</code></pre>\n<h2>Other Escape Characters</h2>\n<p>Here is a list:</p>\n<pre><code>\\' - Single Quote.\n\\\" - Double Quote.\n\\$ - PHP Variables.\n\\n - New Line.\n\\r - Carriage Return.\n\\t - Tab.\n\\f - Form Feed.\n\\ooo - Octal Value.\n\\xhh - Hex Value.\n</code></pre>",
  "title": "PHP Escape Characters",
  "date": "July 12, 2025",
  "category": "PHP 7",
  "categories": []
}