{
  "id": "php/multidimensionalarrays",
  "contentHtml": "<h1>Multidimensional Arrays</h1>\n<p>Arrays inside arrays.</p>\n<ul>\n<li>That's really it.</li>\n</ul>\n<pre><code class=\"language-html\"><span class=\"hljs-meta\">&#x3C;!DOCTYPE <span class=\"hljs-keyword\">html</span>></span>\n<span class=\"hljs-tag\">&#x3C;<span class=\"hljs-name\">html</span>></span>\n\n<span class=\"hljs-tag\">&#x3C;<span class=\"hljs-name\">body</span>></span>\n<span class=\"hljs-meta\">&#x3C;?php\n    $cars = [\n        [\"Toyota\", 1000],\n        [\"Honda\", 1200],\n        [\"Lexus\", 1400]\n    ];\n\n    for ($r = 0; $r &#x3C; 3; $r++) {\n        echo \"Row number $r\";\n\n        echo \"&#x3C;ul>\";\n        for ($c = 0; $c &#x3C; 2; $c++) {\n            echo \"&#x3C;li>\" . $cars[$r][$c] . \"&#x3C;/li>\";\n        }\n        echo \"&#x3C;/ul>\";\n    }\n?></span>\n<span class=\"hljs-tag\">&#x3C;/<span class=\"hljs-name\">body</span>></span>\n\n<span class=\"hljs-tag\">&#x3C;/<span class=\"hljs-name\">html</span>></span>\n</code></pre>",
  "title": "Multidimensial Arrays",
  "date": "July 12, 2025",
  "category": "PHP 7",
  "categories": []
}